BrowserstackLibrary/__init__.py
BrowserstackLibrary/keywords/__init__.py
BrowserstackLibrary/keywords/_updatetestcase.py
BrowserstackLibrary/keywords/_uploadapplication.py
BrowserstackLibrary/utils/__init__.py
BrowserstackLibrary/utils/_browserstackClient.py
BrowserstackLibrary/version.py
robotframework_browserstack-0.1.1.dist-info/LICENSE
robotframework_browserstack-0.1.1.dist-info/METADATA
robotframework_browserstack-0.1.1.dist-info/WHEEL
robotframework_browserstack-0.1.1.dist-info/RECORD
